{
  "game_version": "12.12",
  "location": {
    "maps": [
      {
        "name": "Customs",
        "match_duration_day": 40,
        "match_duration_night": 40,
        "player_count": "9-12",
        "released?": true
      },
      {
        "name": "Factory",
        "match_duration_day": 20,
        "match_duration_night": 25,
        "player_count": "4-6",
        "released?": true
      },
      {
        "name": "Interchange",
        "match_duration_day": 40,
        "match_duration_night": 40,
        "player_count": "10-14",
        "released?": true
      },
      {
        "name": "Lighthouse",
        "match_duration_day": 40,
        "match_duration_night": 40,
        "player_count": "9-12",
        "released?": true
      },
      {
        "name": "Reserve",
        "match_duration_day": 40,
        "match_duration_night": 40,
        "player_count": "9-12",
        "released?": true
      },
      {
        "name": "Shoreline",
        "match_duration_day": 45,
        "match_duration_night": 45,
        "player_count": "10-13",
        "released?": true
      },
      {
        "name": "The Lab",
        "match_duration_day": 35,
        "match_duartion_night": 35,
        "player_count": "6-10",
        "relased?": true
      },
      {
        "name": "Woods",
        "match_duration_day": 40,
        "match_duration_night": 40,
        "player_count": "9-14",
        "released?": true
      },
      {
        "name": "Arena",
        "released?": false
      },
      {
        "name": "Private Sector",
        "released?": false
      },
      {
        "name": "Streets of Tarkov",
        "released?": false
      },
      {
        "name": "Suburbs",
        "released?": false
      },
      {
        "name": "Terminal",
        "released?": false
      },
      {
        "name": "Town",
        "released?": false
      }
    ]
  },
  "hideout": {
    "hideout_stations": [
      {
        "name": "Air Filtering Unit",
        "upgrade_levels": [1]
      },
      {
        "name": "Bitcoin Farm",
        "upgrade_levels": [1, 2, 3]
      },
      {
        "name": "Booze Generator",
        "upgrade_levels": [1]
      },
      {
        "name": "Generator",
        "upgrade_levels": [1, 2, 3]
      },
      {
        "name": "Heating",
        "upgrade_levels": [1, 2, 3]
      },
      {
        "name": "Illumination",
        "upgrade_levels": [1, 2, 3]
      },
      {
        "name": "Intelligence Center",
        "upgrade_levels": [1, 2, 3]
      },
      {
        "name": "Lavatory",
        "upgrade_levels": [1, 2, 3]
      },
      {
        "name": "Library",
        "upgrade_levels": [1]
      },
      {
        "name": "Medstation",
        "upgrade_levels": [1, 2, 3]
      },
      {
        "name": "Nutrition Unit",
        "upgrade_levels": [1, 2, 3]
      },
      {
        "name": "Rest Space",
        "upgrade_levels": [1, 2, 3]
      },
      {
        "name": "Scav Case",
        "upgrade_levels": [1]
      },
      {
        "name": "Security",
        "upgrade_levels": [1, 2, 3]
      },
      {
        "name": "Shooting Range",
        "upgrade_levels": [1]
      },
      {
        "name": "Solar Power",
        "upgrade_levels": [1]
      },
      {
        "name": "Stash",
        "upgrade_levels": [1, 2, 3, 4]
      },
      {
        "name": "Vents",
        "upgrade_levels": [1, 2, 3]
      },
      {
        "name": "Water Collector",
        "upgrade_levels": [1, 2, 3]
      },
      {
        "name": "Workbench",
        "upgrade_levels": [1, 2, 3]
      },
      {
        "name": "Christmas Tree",
        "upgrade_levels": [1]
      }
    ]
  },
  "traders": [
    {
      "title": "Fence",
      "loyalty_levels": [1, 4]
    },
    {
      "title": "Jaeger",
      "loyalty_levels": [1, 2, 3, 4]
    },
    {
      "title": "Mechanic",
      "loyalty_levels": [1, 2, 3, 4]
    },
    {
      "title": "Peacekeeper",
      "loyalty_levels": [1, 2, 3, 4]
    },
    {
      "title": "Prapor",
      "loyalty_levels": [1, 2, 3, 4]
    },
    {
      "title": "Ragman",
      "loyalty_levels": [1, 2, 3, 4]
    },
    {
      "title": "Skier",
      "loyalty_levels": [1, 2, 3, 4]
    },
    {
      "title": "Therapist",
      "loyalty_levels": [1, 2, 3, 4]
    }
  ],
  "handbook": {
    "barter_items": {
      "building_materials": [],
      "electronics": [],
      "energy_elements": [],
      "flammable_materials": [],
      "others": [],
      "household_materials": [],
      "medical_supplies": [],
      "tools": [],
      "valuables": [],
      "info_items": [],
      "special_equipment": []
    },

    "gear": {
      "backpacks": [],
      "body_armor": [],
      "eyewear": [],
      "facecovers": [],
      "gear_components": [],
      "headgear": [],
      "headsets": [],
      "secure_containers": [],
      "storage_containers": [],
      "tactical_rigs": []
    },
    "weapon_parts_&_mods": {
      "functional_mods": {
        "auxiliary_parts": [],
        "bipods": [],
        "foregrips": [],
        "light_&_laser_devices": {
          "flashlights": [],
          "laser_target_designators": [],
          "tactical_combo_devices": []
        },
        "muzzle_devices": {
          "flashhiders": [],
          "muzzle_adapters": [],
          "suppressors": []
        },
        "sights": {
          "assault_scopes": [],
          "collimators": [],
          "compact_collimators": [],
          "iron_sights": [],
          "optics": [],
          "special_purpose_sights": []
        }
      },
      "gear_mods": {
        "charging_handles": [],
        "magazines": [],
        "mounts": [],
        "stocks_&_chassis": []
      },
      "vital_parts": {
        "barrels": [],
        "gas_blocks": [],
        "handguards": [],
        "pistol_grips": [],
        "receievers_&_slides": []
      }
    },
    "weapons": {
      "assault_carbines": [],
      "assault_rifles": [],
      "bolt_action_rifles": [],
      "machine_guns": [],
      "marksman_rifles": [],
      "melee_weapons": [],
      "pistols": [],
      "smgs": [],
      "shotguns": [],
      "special_weapons": [],
      "throwables": []
    },
    "ammo": {
      "ammo_packs": [],
      "rounds": []
    },
    "provisions": {
      "food": [],
      "drinks": []
    },
    "medication": {
      "injectors": [],
      "injury_treatment": [],
      "medkits": [],
      "pills": []
    },
    "keys": {
      "electronic_keys": [],
      "mechanical_keys": []
    },
    "info_items": [],
    "special_equipment": [],
    "maps": [],
    "money": [],
    "quest_items": []
  }
}
